promptwatch/__init__.py
promptwatch/caching.py
promptwatch/client.py
promptwatch/constants.py
promptwatch/data_model.py
promptwatch/decorators.py
promptwatch/promptwatch_context.py
promptwatch/utils.py
promptwatch/langchain/__init__.py
promptwatch/langchain/caching.py
promptwatch/langchain/langchain_support.py
promptwatch/langchain/unit_tests.py
promptwatch/unit_tests/__init__.py
promptwatch/unit_tests/evaluation.py
promptwatch/unit_tests/schema.py
promptwatch/unit_tests/unit_tests.py
promptwatch-0.4.6.dist-info/METADATA
promptwatch-0.4.6.dist-info/WHEEL
promptwatch-0.4.6.dist-info/top_level.txt
promptwatch-0.4.6.dist-info/RECORD
