Metadata-Version: 2.1
Name: promptwatch
Version: 0.4.6
Summary: promptwatch.io python client to trace langchain sessions
Home-page: https://github.com/blip-solutions/promptwatch-client
Author: Juraj Bezdek
Author-email: juraj.bezdek@blip.solutions
License: MIT License
Keywords: promptwatch prompt monitoring
Requires-Python: >=3.8
Requires-Dist: langchain
Requires-Dist: pydantic
Requires-Dist: tiktoken
Requires-Dist: tqdm
